codesave/__init__.py
codesave/base.py
codesave/routines.py
code_save-0.0.1.dist-info/LICENSE
code_save-0.0.1.dist-info/METADATA
code_save-0.0.1.dist-info/WHEEL
code_save-0.0.1.dist-info/top_level.txt
code_save-0.0.1.dist-info/RECORD
