Metadata-Version: 2.1
Name: code-save
Version: 0.0.1
Summary: Save codebases and load them later -- for reproducibility, sharing, loading artifacts in the future.
Author-email: Dibya Ghosh <dibya.ghosh@berkeley.edu>
Project-URL: Homepage, https://github.com/dibyaghosh/codesave
Classifier: Programming Language :: Python :: 3
Classifier: License :: OSI Approved :: MIT License
Classifier: Operating System :: OS Independent
Requires-Python: >=3.8
License-File: LICENSE
